spatialreasoners/__init__.py
spatialreasoners/_main.py
spatialreasoners/api.py
spatialreasoners/config.py
spatialreasoners/env.py
spatialreasoners/global_cfg.py
spatialreasoners/main.py
spatialreasoners/registry.py
spatialreasoners/type_extensions.py
spatialreasoners/benchmark/__init__.py
spatialreasoners/benchmark/benchmark.py
spatialreasoners/benchmark/evaluation/__init__.py
spatialreasoners/benchmark/evaluation/evaluation.py
spatialreasoners/benchmark/evaluation/sampling_evaluation.py
spatialreasoners/benchmark/evaluation/type_extensions.py
spatialreasoners/benchmark/evaluation/frame_vis_sampling_evaluation/__init__.py
spatialreasoners/benchmark/evaluation/frame_vis_sampling_evaluation/frame_vis_sampling_evaluation.py
spatialreasoners/benchmark/evaluation/frame_vis_sampling_evaluation/video_pose_sampling_evaluation.py
spatialreasoners/benchmark/evaluation/frame_vis_sampling_evaluation/image_sampling_evaluation/__init__.py
spatialreasoners/benchmark/evaluation/frame_vis_sampling_evaluation/image_sampling_evaluation/counting_polygons_evaluation.py
spatialreasoners/benchmark/evaluation/frame_vis_sampling_evaluation/image_sampling_evaluation/even_pixels_evaluation.py
spatialreasoners/benchmark/evaluation/frame_vis_sampling_evaluation/image_sampling_evaluation/image_sampling_evaluation.py
spatialreasoners/benchmark/evaluation/frame_vis_sampling_evaluation/image_sampling_evaluation/mnist_evaluation.py
spatialreasoners/benchmark/evaluation/frame_vis_sampling_evaluation/image_sampling_evaluation/mnist_grid_evaluation.py
spatialreasoners/benchmark/evaluation/frame_vis_sampling_evaluation/image_sampling_evaluation/mnist_sudoku_evaluation.py
spatialreasoners/benchmark/evaluation/inference_sampler/__init__.py
spatialreasoners/benchmark/evaluation/inference_sampler/inference_sampler.py
spatialreasoners/benchmark/evaluation/inference_sampler/scheduled_inference_sampler.py
spatialreasoners/benchmark/evaluation/inference_sampler/type_extensions.py
spatialreasoners-1.0.5.dist-info/licenses/LICENSE
spatialreasoners-1.0.5.dist-info/METADATA
spatialreasoners-1.0.5.dist-info/WHEEL
spatialreasoners-1.0.5.dist-info/top_level.txt
spatialreasoners-1.0.5.dist-info/RECORD
