Metadata-Version: 2.4
Name: spatialreasoners
Version: 1.0.5
Summary: SpatialReasoners: A framework for training Spatial Reasoning Models in any domain
Author-email: Bart Pogodzinski <bpogodzi@mpi-inf.mpg.de>, Christopher Wewer <cwewer@mpi-inf.mpg.de>, Jan Eric Lenssen <jlenssen@mpi-inf.mpg.de>, Bernt Schiele <schiele@mpi-inf.mpg.de>
License-Expression: MIT
Project-URL: Homepage, https://github.com/spatialreasoners/spatialreasoners
Project-URL: Documentation, https://spatialreasoners.github.io/
Project-URL: Repository, https://github.com/spatialreasoners/spatialreasoners
Project-URL: Issues, https://github.com/spatialreasoners/spatialreasoners/issues
Keywords: machine learning,deep learning,spatial reasoning,pytorch,pytorch lightning,diffusion models,Spatial Reasoners,SRM
Classifier: Development Status :: 3 - Alpha
Classifier: Intended Audience :: Developers
Classifier: Intended Audience :: Science/Research
Classifier: Programming Language :: Python :: 3
Classifier: Programming Language :: Python :: 3.11
Classifier: Programming Language :: Python :: 3.12
Classifier: Programming Language :: Python :: 3.13
Classifier: Topic :: Scientific/Engineering :: Artificial Intelligence
Classifier: Topic :: Software Development :: Libraries :: Python Modules
Requires-Python: >=3.11
License-File: LICENSE
Requires-Dist: torch>=1.13.0
Requires-Dist: pytorch-lightning>=2.0.0
Requires-Dist: torchvision>=0.14.0
Requires-Dist: torchaudio>=0.13.0
Requires-Dist: hydra-core>=1.3.0
Requires-Dist: omegaconf>=2.3.0
Requires-Dist: dacite>=1.8.0
Requires-Dist: numpy>=1.21.0
Requires-Dist: einops>=0.6.0
Requires-Dist: jaxtyping>=0.2.20
Requires-Dist: beartype>=0.15.0
Requires-Dist: pillow>=8.0.0
Requires-Dist: matplotlib>=3.5.0
Requires-Dist: seaborn>=0.11.0
Requires-Dist: wandb>=0.13.0
Requires-Dist: tensorboard>=2.10.0
Requires-Dist: av>=10.0.0
Requires-Dist: accelerate>=0.20.0
Requires-Dist: diffusers>=0.21.0
Requires-Dist: timm>=0.9.0
Requires-Dist: scipy>=1.9.0
Requires-Dist: pandas>=1.5.0
Requires-Dist: rotary-embedding-torch>=0.2.0
Requires-Dist: roma>=1.3.0
Requires-Dist: tqdm>=4.64.0
Requires-Dist: colorama>=0.4.0
Requires-Dist: gdown>=4.7.0
Requires-Dist: colorspacious>=1.1.0
Provides-Extra: dev
Requires-Dist: pytest>=7.0.0; extra == "dev"
Requires-Dist: pytest-cov>=4.0.0; extra == "dev"
Requires-Dist: pytest-beartype>=0.2.0; extra == "dev"
Requires-Dist: black>=22.0.0; extra == "dev"
Requires-Dist: isort>=5.10.0; extra == "dev"
Requires-Dist: flake8>=5.0.0; extra == "dev"
Requires-Dist: mypy>=0.991; extra == "dev"
Requires-Dist: pre-commit>=2.20.0; extra == "dev"
Provides-Extra: docs
Requires-Dist: sphinx>=5.0.0; extra == "docs"
Requires-Dist: sphinx-rtd-theme>=1.0.0; extra == "docs"
Requires-Dist: myst-parser>=0.18.0; extra == "docs"
Provides-Extra: all
Requires-Dist: spatialreasoners[dev,docs]; extra == "all"
Dynamic: license-file
